[{"startMs":0,"durationMs":3360,"subtitle":"do you know anything about this Mna"},{"startMs":1400,"durationMs":4040,"subtitle":"Henson lady that got in contact with"},{"startMs":3360,"durationMs":5600,"subtitle":"Paul through the highway patrol officer"},{"startMs":5440,"durationMs":6480,"subtitle":"Gabe valdis where she described a story"},{"startMs":8960,"durationMs":5480,"subtitle":"uh involving UFOs bright lights and"},{"startMs":11920,"durationMs":5160,"subtitle":"herds of cattle being abducted and human"},{"startMs":14440,"durationMs":4160,"subtitle":"abductions underground bases yes we we"},{"startMs":17080,"durationMs":4560,"subtitle":"did we there were a number of things"},{"startMs":18600,"durationMs":5160,"subtitle":"that uh blossomed from the Paul benowitz"},{"startMs":21640,"durationMs":4760,"subtitle":"case the Moonah Hansen case the"},{"startMs":23760,"durationMs":5200,"subtitle":"abduction case also the interference of"},{"startMs":26400,"durationMs":5160,"subtitle":"the case by Leo sprinkle and Helen"},{"startMs":28960,"durationMs":5240,"subtitle":"heinik both of them were threatened to"},{"startMs":31560,"durationMs":6400,"subtitle":"be federally prosecuted and they backed"},{"startMs":34200,"durationMs":5839,"subtitle":"away and M Hansen was a 27-year-old I"},{"startMs":37960,"durationMs":4240,"subtitle":"should say uneducated woman with a"},{"startMs":40039,"durationMs":4520,"subtitle":"7-year-old son uh she lived in Northern"},{"startMs":42200,"durationMs":5800,"subtitle":"New Mexico State Police Officer Gabe"},{"startMs":44559,"durationMs":5961,"subtitle":"Valdez first met her when she uh was"},{"startMs":48000,"durationMs":5079,"subtitle":"abducted by"},{"startMs":50520,"durationMs":4240,"subtitle":"extraterrestrials and her son was found"},{"startMs":53079,"durationMs":3221,"subtitle":"in one location and she was found in"},{"startMs":54760,"durationMs":4160,"subtitle":"another"},{"startMs":56300,"durationMs":5620,"subtitle":"[Music]"},{"startMs":58920,"durationMs":3000,"subtitle":"location"}]
