[{"startMs":0,"durationMs":5279,"subtitle":"in our everyday life most things are"},{"startMs":2300,"durationMs":2979,"subtitle":""},{"startMs":2310,"durationMs":5789,"subtitle":"generally normal and routine a bird a"},{"startMs":5269,"durationMs":2830,"subtitle":""},{"startMs":5279,"durationMs":5280,"subtitle":"tree a city block a drive home from work"},{"startMs":8089,"durationMs":2470,"subtitle":""},{"startMs":8099,"durationMs":5311,"subtitle":"a meal a load of laundry a night of"},{"startMs":10549,"durationMs":2861,"subtitle":""},{"startMs":10559,"durationMs":5071,"subtitle":"sleep and so on after a certain age of"},{"startMs":13400,"durationMs":2230,"subtitle":""},{"startMs":13410,"durationMs":4440,"subtitle":"adolescence most things begin to fall"},{"startMs":15620,"durationMs":2230,"subtitle":""},{"startMs":15630,"durationMs":4979,"subtitle":"into this category of averageness or"},{"startMs":17840,"durationMs":2769,"subtitle":""},{"startMs":17850,"durationMs":5040,"subtitle":"tediousness this can for obvious reasons"},{"startMs":20599,"durationMs":2291,"subtitle":""},{"startMs":20609,"durationMs":4910,"subtitle":"post problems on our experience of life"},{"startMs":22880,"durationMs":2639,"subtitle":""},{"startMs":22890,"durationMs":5490,"subtitle":"a frequent sense of boredom and monotony"},{"startMs":25509,"durationMs":2871,"subtitle":""},{"startMs":25519,"durationMs":4361,"subtitle":"science religions and philosophies often"},{"startMs":28370,"durationMs":1510,"subtitle":""},{"startMs":28380,"durationMs":3600,"subtitle":"work to provide us with answers and"},{"startMs":29870,"durationMs":2110,"subtitle":""},{"startMs":29880,"durationMs":4019,"subtitle":"clarity about the universe and our"},{"startMs":31970,"durationMs":1929,"subtitle":""},{"startMs":31980,"durationMs":4020,"subtitle":"existence within it we seek to learn"},{"startMs":33889,"durationMs":2111,"subtitle":""},{"startMs":33899,"durationMs":4680,"subtitle":"about what we as a collective species"},{"startMs":35990,"durationMs":2589,"subtitle":""},{"startMs":36000,"durationMs":5070,"subtitle":"know about ourselves and this reality in"},{"startMs":38569,"durationMs":2501,"subtitle":""},{"startMs":38579,"durationMs":4531,"subtitle":"order to aid our experience of it this"},{"startMs":41060,"durationMs":2050,"subtitle":""},{"startMs":41070,"durationMs":4169,"subtitle":"can be helpful of course but perhaps an"},{"startMs":43100,"durationMs":2139,"subtitle":""},{"startMs":43110,"durationMs":5250,"subtitle":"equally valuable and often neglected"},{"startMs":45229,"durationMs":3131,"subtitle":""},{"startMs":45239,"durationMs":5431,"subtitle":"source of wisdom joy and vitality can be"},{"startMs":48350,"durationMs":2320,"subtitle":""},{"startMs":48360,"durationMs":5060,"subtitle":"found not in what we know but in what we"},{"startMs":50660,"durationMs":2760,"subtitle":""},{"startMs":50670,"durationMs":5610,"subtitle":"don't know a deep contemplation and"},{"startMs":53410,"durationMs":2870,"subtitle":""},{"startMs":53420,"durationMs":6729,"subtitle":"assimilation of the unknown into our"},{"startMs":56270,"durationMs":3879,"subtitle":""},{"startMs":56280,"durationMs":6060,"subtitle":"daily life 19th century writer Henry"},{"startMs":60139,"durationMs":2201,"subtitle":""},{"startMs":60149,"durationMs":4590,"subtitle":"David Thoreau writes my desire for"},{"startMs":62330,"durationMs":2409,"subtitle":""},{"startMs":62340,"durationMs":3930,"subtitle":"knowledge is intermittent but my desire"},{"startMs":64729,"durationMs":1541,"subtitle":""},{"startMs":64739,"durationMs":3691,"subtitle":"to commune with the spirit of the"},{"startMs":66260,"durationMs":2170,"subtitle":""},{"startMs":66270,"durationMs":5370,"subtitle":"universe to be intoxicated with the"},{"startMs":68420,"durationMs":3220,"subtitle":""},{"startMs":68430,"durationMs":4830,"subtitle":"fumes call it of that divine nectar to"},{"startMs":71630,"durationMs":1630,"subtitle":""},{"startMs":71640,"durationMs":3720,"subtitle":"bear my head through atmospheres and"},{"startMs":73250,"durationMs":2110,"subtitle":""},{"startMs":73260,"durationMs":5280,"subtitle":"over Heights unknown to my feet is"},{"startMs":75350,"durationMs":3190,"subtitle":""},{"startMs":75360,"durationMs":5369,"subtitle":"perennial and constant which is to say"},{"startMs":78530,"durationMs":2199,"subtitle":""},{"startMs":78540,"durationMs":4469,"subtitle":"the experience and effects of concrete"},{"startMs":80719,"durationMs":2290,"subtitle":""},{"startMs":80729,"durationMs":4651,"subtitle":"knowledge can be fleeting but the wonder"},{"startMs":82999,"durationMs":2381,"subtitle":""},{"startMs":83009,"durationMs":5371,"subtitle":"found in the spirit of the unknown can"},{"startMs":85370,"durationMs":3010,"subtitle":""},{"startMs":85380,"durationMs":4919,"subtitle":"be constant and enduring with no more"},{"startMs":88370,"durationMs":1929,"subtitle":""},{"startMs":88380,"durationMs":4320,"subtitle":"than a glance upward at a clear starry"},{"startMs":90289,"durationMs":2411,"subtitle":""},{"startMs":90299,"durationMs":4741,"subtitle":"night sky as we stare into the eyes of"},{"startMs":92690,"durationMs":2350,"subtitle":""},{"startMs":92700,"durationMs":4529,"subtitle":"the incomprehensible and infinite space"},{"startMs":95030,"durationMs":2199,"subtitle":""},{"startMs":95040,"durationMs":4259,"subtitle":"above us we are likely to experience an"},{"startMs":97219,"durationMs":2080,"subtitle":""},{"startMs":97229,"durationMs":4831,"subtitle":"overwhelming awareness of how little we"},{"startMs":99289,"durationMs":2771,"subtitle":""},{"startMs":99299,"durationMs":4741,"subtitle":"know and how little we are the universe"},{"startMs":102050,"durationMs":1990,"subtitle":""},{"startMs":102060,"durationMs":4559,"subtitle":"stares back at us with its stark glare"},{"startMs":104030,"durationMs":2589,"subtitle":""},{"startMs":104040,"durationMs":5100,"subtitle":"and reminds us how deeply strange and"},{"startMs":106609,"durationMs":2531,"subtitle":""},{"startMs":106619,"durationMs":4921,"subtitle":"unclear our life really is even in the"},{"startMs":109130,"durationMs":2410,"subtitle":""},{"startMs":109140,"durationMs":5130,"subtitle":"most simple and normal the great"},{"startMs":111530,"durationMs":2740,"subtitle":""},{"startMs":111540,"durationMs":5340,"subtitle":"cosmologists Carl Sagan said the cosmos"},{"startMs":114260,"durationMs":2620,"subtitle":""},{"startMs":114270,"durationMs":4860,"subtitle":"is all that is or was or ever will be"},{"startMs":116870,"durationMs":2260,"subtitle":""},{"startMs":116880,"durationMs":5010,"subtitle":"our feeblest contemplations of the"},{"startMs":119120,"durationMs":2770,"subtitle":""},{"startMs":119130,"durationMs":5279,"subtitle":"cosmos stir us there's a tingling in the"},{"startMs":121880,"durationMs":2529,"subtitle":""},{"startMs":121890,"durationMs":4950,"subtitle":"spine a catch in the voice a faint"},{"startMs":124399,"durationMs":2441,"subtitle":""},{"startMs":124409,"durationMs":4621,"subtitle":"sensation as if a distant memory of"},{"startMs":126830,"durationMs":2200,"subtitle":""},{"startMs":126840,"durationMs":4050,"subtitle":"falling from a height this feeling of"},{"startMs":129020,"durationMs":1870,"subtitle":""},{"startMs":129030,"durationMs":4200,"subtitle":"awe is immensely liberating and"},{"startMs":130880,"durationMs":2350,"subtitle":""},{"startMs":130890,"durationMs":2550,"subtitle":"provoking it reminds us that we stand at"},{"startMs":133220,"durationMs":220,"subtitle":""},{"startMs":133230,"durationMs":2250,"subtitle":"the"},{"startMs":133430,"durationMs":2050,"subtitle":""},{"startMs":133440,"durationMs":4500,"subtitle":"crossroads of the infinite in the finite"},{"startMs":135470,"durationMs":2470,"subtitle":""},{"startMs":135480,"durationMs":5490,"subtitle":"the everything and the nothing the"},{"startMs":137930,"durationMs":3040,"subtitle":""},{"startMs":137940,"durationMs":4620,"subtitle":"knowing and the unknowing in truth no"},{"startMs":140960,"durationMs":1600,"subtitle":""},{"startMs":140970,"durationMs":3540,"subtitle":"matter what we think we know we are"},{"startMs":142550,"durationMs":1960,"subtitle":""},{"startMs":142560,"durationMs":3690,"subtitle":"probably wrong and no matter what anyone"},{"startMs":144500,"durationMs":1750,"subtitle":""},{"startMs":144510,"durationMs":4470,"subtitle":"else thinks they know they are probably"},{"startMs":146240,"durationMs":2740,"subtitle":""},{"startMs":146250,"durationMs":4320,"subtitle":"wrong nobody ever figures out what life"},{"startMs":148970,"durationMs":1600,"subtitle":""},{"startMs":148980,"durationMs":4260,"subtitle":"is all about and it doesn't matter"},{"startMs":150560,"durationMs":2680,"subtitle":""},{"startMs":150570,"durationMs":4530,"subtitle":"explore the world nearly everything is"},{"startMs":153230,"durationMs":1870,"subtitle":""},{"startMs":153240,"durationMs":3990,"subtitle":"really interesting if you go into it"},{"startMs":155090,"durationMs":2140,"subtitle":""},{"startMs":155100,"durationMs":4830,"subtitle":"deeply enough said renowned theoretical"},{"startMs":157220,"durationMs":2710,"subtitle":""},{"startMs":157230,"durationMs":4860,"subtitle":"physicist Richard Feynman at this point"},{"startMs":159920,"durationMs":2170,"subtitle":""},{"startMs":159930,"durationMs":4410,"subtitle":"no one truly knows what's going on in"},{"startMs":162080,"durationMs":2260,"subtitle":""},{"startMs":162090,"durationMs":4560,"subtitle":"any fundamental sense nothing about this"},{"startMs":164330,"durationMs":2320,"subtitle":""},{"startMs":164340,"durationMs":4500,"subtitle":"life is simple or clear and nothing down"},{"startMs":166640,"durationMs":2200,"subtitle":""},{"startMs":166650,"durationMs":4260,"subtitle":"here on earth including us from the"},{"startMs":168830,"durationMs":2080,"subtitle":""},{"startMs":168840,"durationMs":4400,"subtitle":"perspective of the stars matters all"},{"startMs":170900,"durationMs":2340,"subtitle":""},{"startMs":170910,"durationMs":4590,"subtitle":"that much to anything beyond itself"},{"startMs":173230,"durationMs":2270,"subtitle":""},{"startMs":173240,"durationMs":4470,"subtitle":"paradoxically in this we find great"},{"startMs":175490,"durationMs":2220,"subtitle":""},{"startMs":175500,"durationMs":4860,"subtitle":"opportunity for wisdom humility"},{"startMs":177700,"durationMs":2660,"subtitle":""},{"startMs":177710,"durationMs":5320,"subtitle":"exploration and profound experience in"},{"startMs":180350,"durationMs":2680,"subtitle":""},{"startMs":180360,"durationMs":5160,"subtitle":"even the most common in mundane there is"},{"startMs":183020,"durationMs":2500,"subtitle":""},{"startMs":183030,"durationMs":4860,"subtitle":"complexity and strangeness we don't even"},{"startMs":185510,"durationMs":2380,"subtitle":""},{"startMs":185520,"durationMs":4050,"subtitle":"know why we sleep or dream we don't know"},{"startMs":187880,"durationMs":1690,"subtitle":""},{"startMs":187890,"durationMs":3600,"subtitle":"how most of our brain works or what"},{"startMs":189560,"durationMs":1930,"subtitle":""},{"startMs":189570,"durationMs":4050,"subtitle":"consciousness is we don't know if time"},{"startMs":191480,"durationMs":2140,"subtitle":""},{"startMs":191490,"durationMs":4200,"subtitle":"is real in any physical sense we don't"},{"startMs":193610,"durationMs":2080,"subtitle":""},{"startMs":193620,"durationMs":3600,"subtitle":"know what gravity is or why it is we"},{"startMs":195680,"durationMs":1540,"subtitle":""},{"startMs":195690,"durationMs":3960,"subtitle":"don't know if there are infinite other"},{"startMs":197210,"durationMs":2440,"subtitle":""},{"startMs":197220,"durationMs":4440,"subtitle":"universes or dimensions around us right"},{"startMs":199640,"durationMs":2020,"subtitle":""},{"startMs":199650,"durationMs":4020,"subtitle":"now we don't know why energy or matter"},{"startMs":201650,"durationMs":2020,"subtitle":""},{"startMs":201660,"durationMs":3390,"subtitle":"even came to be in the first place or"},{"startMs":203660,"durationMs":1390,"subtitle":""},{"startMs":203670,"durationMs":3390,"subtitle":"why it was followed by a perfect"},{"startMs":205040,"durationMs":2020,"subtitle":""},{"startMs":205050,"durationMs":4140,"subtitle":"sequence of colliding combining"},{"startMs":207050,"durationMs":2140,"subtitle":""},{"startMs":207060,"durationMs":5490,"subtitle":"exploding and emerging all to put us"},{"startMs":209180,"durationMs":3370,"subtitle":""},{"startMs":209190,"durationMs":5340,"subtitle":"here right now able to ask why at the"},{"startMs":212540,"durationMs":1990,"subtitle":""},{"startMs":212550,"durationMs":4530,"subtitle":"base of almost everything the resulting"},{"startMs":214520,"durationMs":2560,"subtitle":""},{"startMs":214530,"durationMs":4650,"subtitle":"statement is we don't know when we"},{"startMs":217070,"durationMs":2110,"subtitle":""},{"startMs":217080,"durationMs":4200,"subtitle":"disregard this unknowingness we can"},{"startMs":219170,"durationMs":2110,"subtitle":""},{"startMs":219180,"durationMs":4440,"subtitle":"easily become disinterested uninspired"},{"startMs":221270,"durationMs":2350,"subtitle":""},{"startMs":221280,"durationMs":3690,"subtitle":"and worn out of this life we can put"},{"startMs":223610,"durationMs":1360,"subtitle":""},{"startMs":223620,"durationMs":3450,"subtitle":"great stress on things that perhaps"},{"startMs":224960,"durationMs":2110,"subtitle":""},{"startMs":224970,"durationMs":4680,"subtitle":"don't matter all that much and neglect"},{"startMs":227060,"durationMs":2590,"subtitle":""},{"startMs":227070,"durationMs":4260,"subtitle":"our experiences and things that do we"},{"startMs":229640,"durationMs":1690,"subtitle":""},{"startMs":229650,"durationMs":4050,"subtitle":"can feel the pressure and anxiety of"},{"startMs":231320,"durationMs":2380,"subtitle":""},{"startMs":231330,"durationMs":6230,"subtitle":"chasing perfection and certainty which"},{"startMs":233690,"durationMs":3870,"subtitle":""},{"startMs":233700,"durationMs":6539,"subtitle":"of course at this moment do not exist"},{"startMs":237550,"durationMs":2689,"subtitle":""},{"startMs":237560,"durationMs":4660,"subtitle":"alternatively the frequent consideration"},{"startMs":240229,"durationMs":1991,"subtitle":""},{"startMs":240239,"durationMs":4651,"subtitle":"and acceptance of the unknown within"},{"startMs":242210,"durationMs":2680,"subtitle":""},{"startMs":242220,"durationMs":4590,"subtitle":"every moment and in everything can bring"},{"startMs":244880,"durationMs":1930,"subtitle":""},{"startMs":244890,"durationMs":4140,"subtitle":"us back down to our earthly innocence"},{"startMs":246800,"durationMs":2230,"subtitle":""},{"startMs":246810,"durationMs":4560,"subtitle":"and curiosity and open us up to an"},{"startMs":249020,"durationMs":2350,"subtitle":""},{"startMs":249030,"durationMs":4739,"subtitle":"appreciation for all things people and"},{"startMs":251360,"durationMs":2409,"subtitle":""},{"startMs":251370,"durationMs":5280,"subtitle":"ideas we should look to the universe"},{"startMs":253759,"durationMs":2891,"subtitle":""},{"startMs":253769,"durationMs":5190,"subtitle":"often not solely for answers but for a"},{"startMs":256640,"durationMs":2319,"subtitle":""},{"startMs":256650,"durationMs":4320,"subtitle":"perspective for a healthful adjustment"},{"startMs":258949,"durationMs":2021,"subtitle":""},{"startMs":258959,"durationMs":4801,"subtitle":"and aerial consideration of our daily"},{"startMs":260960,"durationMs":2800,"subtitle":""},{"startMs":260970,"durationMs":4199,"subtitle":"life arguably within this practice the"},{"startMs":263750,"durationMs":1419,"subtitle":""},{"startMs":263760,"durationMs":2810,"subtitle":"little things in life become more"},{"startMs":265159,"durationMs":1411,"subtitle":""},{"startMs":265169,"durationMs":3291,"subtitle":"exciting and striking"},{"startMs":266560,"durationMs":1900,"subtitle":""},{"startMs":266570,"durationMs":4590,"subtitle":"the mistakes in the annoyance has become"},{"startMs":268450,"durationMs":2710,"subtitle":""},{"startMs":268460,"durationMs":4920,"subtitle":"less significant the calm becomes easier"},{"startMs":271150,"durationMs":2230,"subtitle":""},{"startMs":271160,"durationMs":5040,"subtitle":"and everyday activities of our life that"},{"startMs":273370,"durationMs":2830,"subtitle":""},{"startMs":273380,"durationMs":5040,"subtitle":"we so often view as wasteful and tedious"},{"startMs":276190,"durationMs":2230,"subtitle":""},{"startMs":276200,"durationMs":4380,"subtitle":"reveal to be wonderfully strange in"},{"startMs":278410,"durationMs":2170,"subtitle":""},{"startMs":278420,"durationMs":3810,"subtitle":"curious parts of our existence that we"},{"startMs":280570,"durationMs":1660,"subtitle":""},{"startMs":280580,"durationMs":5130,"subtitle":"should perhaps make efforts to ponder"},{"startMs":282220,"durationMs":3490,"subtitle":""},{"startMs":282230,"durationMs":5730,"subtitle":"and appreciate as often as we can as if"},{"startMs":285700,"durationMs":2260,"subtitle":""},{"startMs":285710,"durationMs":4110,"subtitle":"to say I'd love to marvel at and enjoy"},{"startMs":287950,"durationMs":1870,"subtitle":""},{"startMs":287960,"durationMs":4260,"subtitle":"this work of art I've created the"},{"startMs":289810,"durationMs":2410,"subtitle":""},{"startMs":289820,"durationMs":4350,"subtitle":"universe gave itself humanity through"},{"startMs":292210,"durationMs":1960,"subtitle":""},{"startMs":292220,"durationMs":4290,"subtitle":"our eyes the universe is perceiving"},{"startMs":294160,"durationMs":2350,"subtitle":""},{"startMs":294170,"durationMs":4680,"subtitle":"itself through our ears of the universe"},{"startMs":296500,"durationMs":2350,"subtitle":""},{"startMs":296510,"durationMs":3810,"subtitle":"is listening to its harmonies we are the"},{"startMs":298840,"durationMs":1480,"subtitle":""},{"startMs":298850,"durationMs":3690,"subtitle":"witnesses through which the universe"},{"startMs":300310,"durationMs":2230,"subtitle":""},{"startMs":300320,"durationMs":5160,"subtitle":"becomes conscious of its glory of its"},{"startMs":302530,"durationMs":2950,"subtitle":""},{"startMs":302540,"durationMs":5790,"subtitle":"magnificence said 20th century American"},{"startMs":305470,"durationMs":2860,"subtitle":""},{"startMs":305480,"durationMs":4410,"subtitle":"British philosopher Allen Watts and what"},{"startMs":308320,"durationMs":1570,"subtitle":""},{"startMs":308330,"durationMs":3960,"subtitle":"a shame it would be to waste this"},{"startMs":309880,"durationMs":2410,"subtitle":""},{"startMs":309890,"durationMs":5100,"subtitle":"experience by denying said glory and"},{"startMs":312280,"durationMs":2710,"subtitle":""},{"startMs":312290,"durationMs":5400,"subtitle":"magnificence in a clear starry night sky"},{"startMs":314980,"durationMs":2710,"subtitle":""},{"startMs":314990,"durationMs":4350,"subtitle":"we see beauty not because we know where"},{"startMs":317680,"durationMs":1660,"subtitle":""},{"startMs":317690,"durationMs":4740,"subtitle":"all the stars came from or where they"},{"startMs":319330,"durationMs":3100,"subtitle":""},{"startMs":319340,"durationMs":4950,"subtitle":"will all go but because we don't in the"},{"startMs":322420,"durationMs":1870,"subtitle":""},{"startMs":322430,"durationMs":3720,"subtitle":"scope of the bigger picture the only"},{"startMs":324280,"durationMs":1870,"subtitle":""},{"startMs":324290,"durationMs":4140,"subtitle":"thing that seems to remain sizeable and"},{"startMs":326140,"durationMs":2290,"subtitle":""},{"startMs":326150,"durationMs":4290,"subtitle":"relevant about us is that we are here"},{"startMs":328420,"durationMs":2020,"subtitle":""},{"startMs":328430,"durationMs":4110,"subtitle":"able to look up to the stars any night"},{"startMs":330430,"durationMs":2110,"subtitle":""},{"startMs":330440,"durationMs":5010,"subtitle":"we'd like during our brief and fleeting"},{"startMs":332530,"durationMs":2920,"subtitle":""},{"startMs":332540,"durationMs":5280,"subtitle":"exploration of this life and wonder why"},{"startMs":335440,"durationMs":2380,"subtitle":""},{"startMs":335450,"durationMs":4830,"subtitle":"they are there we must remember that the"},{"startMs":337810,"durationMs":2470,"subtitle":""},{"startMs":337820,"durationMs":5900,"subtitle":"unknown is always above below and beside"},{"startMs":340270,"durationMs":3450,"subtitle":""},{"startMs":340280,"durationMs":3440,"subtitle":"us whenever we needed"},{"startMs":346290,"subtitle":""},{"startMs":346300,"durationMs":2060,"subtitle":"you"},{"startMs":358830,"subtitle":""},{"startMs":358840,"durationMs":2060,"subtitle":"you"}]
