[{"startMs":4320,"durationMs":4720,"subtitle":"okay let's go on to the last part which is the most difficult part of this uh section"},{"startMs":9040,"durationMs":5280,"subtitle":"talking about money lending money lending and the medieval church is where the shalock of course is"},{"startMs":14320,"durationMs":6400,"subtitle":"the the image he [ __ ] is the merchant of venice and shakespeare's famous play here"},{"startMs":20720,"durationMs":6560,"subtitle":"appropriately indicated with a red hat which was the badge that jews were required to wear in"},{"startMs":27280,"durationMs":6560,"subtitle":"venice at the time of the uh of the setting of this particular play so uh"},{"startMs":34880,"durationMs":7200,"subtitle":"the idea of money lending is uh heavily discouraged by the church specifically"},{"startMs":42640,"durationMs":8160,"subtitle":"uh one christian to another and charging interest uh if you look at deuteronomy chapter 23 verses"},{"startMs":50800,"durationMs":5520,"subtitle":"20 21 it says very clearly you shall not lend on interest to your brother interest of food or"},{"startMs":56320,"durationMs":7200,"subtitle":"money or anything on which interest can be charged you may charge interest to a foreigner but not to"},{"startMs":63520,"durationMs":5120,"subtitle":"your brother now there's a lot more to say about this in terms of jewish thought but basically"},{"startMs":68640,"durationMs":7120,"subtitle":"the way the rabbis understood this for centuries is that fellow jews are brothers and"},{"startMs":75760,"durationMs":5600,"subtitle":"non-jews are not brothers they are in the category of foreigners again there are some interesting"},{"startMs":81360,"durationMs":7840,"subtitle":"exceptions where there were some jewish thinkers who argued that the that christians were brothers"},{"startMs":89200,"durationMs":6080,"subtitle":"as well because they believed in the same god as the jews others disagreed but for the most part"},{"startMs":95280,"durationMs":6800,"subtitle":"this is the way it was understood that a jew was allowed to charge interest to a non-jew now"},{"startMs":102960,"durationMs":6080,"subtitle":"given that jews basically lived in a kind of binary society where there was only christians"},{"startMs":109040,"durationMs":7280,"subtitle":"and jews there are very very few minorities of any other religious denomination so the only people"},{"startMs":116320,"durationMs":4320,"subtitle":"who would be able to technically lend money on interest to christians if christians aren't doing"},{"startMs":120640,"durationMs":8240,"subtitle":"to each other is the jews so they had kind of like a monopoly on the entire possibility of of"},{"startMs":130000,"durationMs":8480,"subtitle":"money lending the the church tried to deal with this in some ways a fourth century thinker ambrose"},{"startMs":138480,"durationMs":5520,"subtitle":"argued that it's a very beautiful thing for christians to lend money and not charge interest"},{"startMs":144000,"durationMs":7040,"subtitle":"to each other kind of like a gemach kind of free loan society but it was uh you know hard to"},{"startMs":151040,"durationMs":5120,"subtitle":"encourage this because after all there's no profit i mean you have to be independently wealthy and"},{"startMs":156160,"durationMs":6080,"subtitle":"willing to risk your money to lend money without charging interest so it just it was not happening"},{"startMs":162240,"durationMs":6160,"subtitle":"and so money landing especially as the economy became more and more sophisticated it became"},{"startMs":168400,"durationMs":7120,"subtitle":"much more necessary to have the institution of credit flowing in society this is especially true"},{"startMs":175520,"durationMs":6000,"subtitle":"if you have an agricultural society where you have farmers who are cash poor they're not"},{"startMs":181520,"durationMs":6400,"subtitle":"actually bringing in coin but they've got to buy seed and they have to like wait a long time until"},{"startMs":187920,"durationMs":6320,"subtitle":"they can harvest so sometimes credit is the only way to bridge that period where they will not have"},{"startMs":194240,"durationMs":7360,"subtitle":"anything to pay for their goods and services for ultimately however the church decreed in the 12th"},{"startMs":201600,"durationMs":6720,"subtitle":"century and the so-called de [ __ ] gratiani also known as the law of gratian here's another on the"},{"startMs":208320,"durationMs":5440,"subtitle":"left by the way you see an illuminated manuscript that illustrates one of the many laws discussed"},{"startMs":213760,"durationMs":5440,"subtitle":"in the tikkaratan graziani actually has to do with whom may marry whom in terms of blood relations"},{"startMs":220080,"durationMs":6640,"subtitle":"but the law of gratian said full stop christians you can't charge each other interest"},{"startMs":227440,"durationMs":8800,"subtitle":"which means effectively jews are the only source of credit in medieval europe and so jews started"},{"startMs":236240,"durationMs":4080,"subtitle":"engaging in money lending again when we think about all the things we talked about"},{"startMs":240320,"durationMs":6480,"subtitle":"in the last two segments about the risks of agriculture the risks of commerce money"},{"startMs":246800,"durationMs":7040,"subtitle":"lending has a lot to speak about it guild membership was a hotly contested element and"},{"startMs":254640,"durationMs":5280,"subtitle":"frequently when jews would establish themselves in particular municipalities"},{"startMs":261120,"durationMs":4320,"subtitle":"the they had to negotiate the rights that they would have when they moved there"},{"startMs":266000,"durationMs":8480,"subtitle":"um and some some cities would simply um negotiate in advance a law did non tolerantes judeas that"},{"startMs":274480,"durationMs":5360,"subtitle":"jews were not allowed to settle there more likely because nobility tended to have a vested interest"},{"startMs":279840,"durationMs":7600,"subtitle":"in having jewish people live there they would negotiate that okay fine jews can move here but no"},{"startMs":287440,"durationMs":8720,"subtitle":"shoemakers okay jews cannot sell shoes or jews can sell shoes but only when they're ready made they"},{"startMs":296160,"durationMs":8000,"subtitle":"can't actually make them so guilds and uh various type of trade unions primitive trade unions often"},{"startMs":304160,"durationMs":6320,"subtitle":"uh restricted the tasks that jews can be involved in now we definitely did have christians who were"},{"startMs":310480,"durationMs":6160,"subtitle":"nevertheless interested in the kind of prophet that jews were involved in so the jews had a"},{"startMs":316640,"durationMs":6400,"subtitle":"monopoly but it was only de ure meaning according to the law the written law de facto they did have"},{"startMs":323040,"durationMs":5280,"subtitle":"to compete with christians and ultimately the the church would find a way around it uh specifically"},{"startMs":328320,"durationMs":4960,"subtitle":"the franciscans and that would be the end of the jewish monopoly although not necessarily the"},{"startMs":333280,"durationMs":5440,"subtitle":"end of jewish money lending for reasons we'll see in just a few minutes so what's going on"},{"startMs":338720,"durationMs":7040,"subtitle":"with usury which is kind of like the nasty word for monday lending the benefits are fantastic"},{"startMs":346880,"durationMs":8000,"subtitle":"it involves a high rate of profit the rate of interest charged was anywhere from 30 percent to"},{"startMs":354880,"durationMs":8640,"subtitle":"200 percent we're talking about loan shark rates it was very very expensive to borrow money and uh"},{"startMs":363520,"durationMs":5280,"subtitle":"so that meant that people who could afford to lend the money could make a massive amount of profit"},{"startMs":369680,"durationMs":5600,"subtitle":"it was an urban profession and jews as we have seen over and over again in the diaspora they"},{"startMs":375280,"durationMs":6640,"subtitle":"have gravitated to urban settings so this is you know something that that makes a lot of"},{"startMs":381920,"durationMs":5520,"subtitle":"sense if you're living like it's like you can have bankers hours you can simply say when you're going"},{"startMs":387440,"durationMs":6240,"subtitle":"to open ten to three and uh then you just let the customers come to you i mean it's it's a fantastic"},{"startMs":393680,"durationMs":7440,"subtitle":"possibility and uh it is portable it's the kind of thing where if you're dealing in cash you know"},{"startMs":401120,"durationMs":7200,"subtitle":"especially when you have lots of contacts through commercial ventures you can deposit money for safe"},{"startMs":408320,"durationMs":6880,"subtitle":"keeping you can exchange letters of credit and so on and it requires fairly minimal effort moreover"},{"startMs":415200,"durationMs":6880,"subtitle":"the jews were actually quite well uh prepared for this because they were literate they were numerate"},{"startMs":422080,"durationMs":7600,"subtitle":"um they they had this this great relationship with the king right the the uh cerve camareires where"},{"startMs":429680,"durationMs":7360,"subtitle":"if they're making money through money lending that means a really great you know flow of currency to"},{"startMs":437040,"durationMs":7760,"subtitle":"the king directly later on uh you know when we get to 18th century poland uh the king would realize"},{"startMs":444800,"durationMs":5520,"subtitle":"if it's so easy for the jews to make money then we want a bigger part of it and ultimately they would"},{"startMs":450880,"durationMs":4480,"subtitle":"take apart the very structure that held it together but that's hundreds of years later in the"},{"startMs":455360,"durationMs":6720,"subtitle":"period we're talking about now the risks however are also commensurate the biggest risk of course"},{"startMs":462080,"durationMs":5360,"subtitle":"is resentment because you know we all have credit cards and nobody likes getting a credit card bill"},{"startMs":467440,"durationMs":4080,"subtitle":"and when you look at the statement and you see okay i bought this i bought this and what"},{"startMs":471520,"durationMs":4880,"subtitle":"interest charge wow you know you feel really bad about it especially if you can't pay off"},{"startMs":476400,"durationMs":4800,"subtitle":"the balance down to zero every month you see that interest charge and every month you're saying wow"},{"startMs":481200,"durationMs":5840,"subtitle":"i'm paying so many dollars for nothing for stuff i bought a long time ago and all already you know"},{"startMs":487040,"durationMs":8880,"subtitle":"gone so there's a great deal of resentment this can come from the peasants um when you know they"},{"startMs":495920,"durationMs":8160,"subtitle":"may borrow small sums but they carry a you know an oppressive debt load and when peasants get too"},{"startMs":504080,"durationMs":6800,"subtitle":"upset then what happens is pogroms you have popular uprisings often against the will of"},{"startMs":510880,"durationMs":6240,"subtitle":"the king who is happy to see the jews engaged in usury and then bringing more funds back to them"},{"startMs":517120,"durationMs":5040,"subtitle":"but if it's too much then the king you know he can't control the peasants under these terms"},{"startMs":522160,"durationMs":6800,"subtitle":"the clergy are often resentful of this because it represents kind of like a a legal fictional"},{"startMs":528960,"durationMs":7680,"subtitle":"fictional go-around or a loophole to the law of gratian because the gravity clearly allows jews to"},{"startMs":536640,"durationMs":4720,"subtitle":"charge interest but you know who wants this kind of thing happening in society even though"},{"startMs":541360,"durationMs":6080,"subtitle":"it is economically necessary and the nobility and even the king however can show resentment because"},{"startMs":547440,"durationMs":8320,"subtitle":"it was not at all that uncommon for nobles and even kings to end up borrowing large sumps among"},{"startMs":555760,"durationMs":5600,"subtitle":"money from jewish populations and then when things don't go their way like for example if they're"},{"startMs":561360,"durationMs":7520,"subtitle":"trying to finance a border war or an expansion of some sort uh then it becomes much more expedient"},{"startMs":568880,"durationMs":7600,"subtitle":"to simply expel the jews and cancel their debts we see this happening frequently in medieval europe"},{"startMs":576480,"durationMs":6320,"subtitle":"england for example expelled their jews in 1290 over basically this issue where it was simply"},{"startMs":582800,"durationMs":7440,"subtitle":"easier to simply say okay do over and as we saw in france as we will see in france the jews will then"},{"startMs":590240,"durationMs":4960,"subtitle":"be invited back a generation later because when they expel the jews then they have no more source"},{"startMs":595200,"durationMs":5280,"subtitle":"of credit they need credit to keep their economy growing so then they invite the jews back they"},{"startMs":600480,"durationMs":4880,"subtitle":"end up borrowing a lot of money becomes too much they expel the jews and they enter into this cycle"},{"startMs":605360,"durationMs":7760,"subtitle":"once again so this is the kind of danger that is associated with uh money lending in this period so"},{"startMs":613120,"durationMs":6880,"subtitle":"the the relative wealth and power that are accumulated through money lending it can be quite"},{"startMs":620560,"durationMs":8240,"subtitle":"ephemeral because of the large-scale resentment that can be built up in the population later"},{"startMs":628800,"durationMs":7280,"subtitle":"on when we get to eastern europe uh in the next semester of these classes some of the elements of"},{"startMs":636080,"durationMs":6880,"subtitle":"this become even greater when alcohol is involved because in eastern europe jews frequently had"},{"startMs":642960,"durationMs":7120,"subtitle":"monopoly on the production of alcohol something called proper nazia and so people could drink on"},{"startMs":650080,"durationMs":6960,"subtitle":"a tab and then end up having you know a huge bill plus an interest charge on top of that you know"},{"startMs":657680,"durationMs":5360,"subtitle":"many of the uh the revolts you'll see in the 17th and 18th century in eastern europe have this at"},{"startMs":663040,"durationMs":7120,"subtitle":"the root the exploitative practices of some of the jewish communities that are are heavily resented"},{"startMs":670160,"durationMs":6320,"subtitle":"by their customers when they have to actually pay the bill for what they've purchased it's a very"},{"startMs":676480,"durationMs":8320,"subtitle":"difficult period definitely now how does this all come to end largely the italians wake up and say"},{"startMs":684800,"durationMs":6080,"subtitle":"they've got to get involved in this so in italy in the middle of the 15th century you have this"},{"startMs":690880,"durationMs":5680,"subtitle":"institution developed by the franciscan order of monks called the monte de pieta which means"},{"startMs":696560,"durationMs":8320,"subtitle":"the the mountains of piety and essentially what they do is they create their own loan societies"},{"startMs":705760,"durationMs":6080,"subtitle":"which have which operate a lot like modern credit unions or banks in fact this is where"},{"startMs":711840,"durationMs":5520,"subtitle":"credit unions and banks begin to get their ideas and and get started they charge interest"},{"startMs":718400,"durationMs":6560,"subtitle":"but it's small interest between 4 and 15 which is much more manageable and the purpose of this"},{"startMs":724960,"durationMs":7520,"subtitle":"interest is largely to cover the overhead of hiring staff to manage the funds and so on and"},{"startMs":732480,"durationMs":8240,"subtitle":"uh they lend to christians at a very low rate of interest but it is approved by the church uh first"},{"startMs":740720,"durationMs":5200,"subtitle":"you know temporarily and then towards the end of the 15th century formally approved by the church"},{"startMs":745920,"durationMs":7280,"subtitle":"because the overhead costs are not uh interest for a profit bearing uh idea they're really there"},{"startMs":753200,"durationMs":7920,"subtitle":"to just keep the system flowing now the demand for credit far outstrips the supply that the"},{"startMs":761120,"durationMs":9440,"subtitle":"monte de pieta are able to uh service but it still means that that the um the jewish monopoly has"},{"startMs":770560,"durationMs":7040,"subtitle":"been pierced that there is no now the church has officially sanctioned this type of banking there"},{"startMs":777600,"durationMs":5680,"subtitle":"is no reason why one would still have to go to a jew but the fact that the demand is still so"},{"startMs":783280,"durationMs":5120,"subtitle":"high far more than the amount of cash in the month of bieter are able to maintain it meant"},{"startMs":788400,"durationMs":6400,"subtitle":"that jewish money lending still continued uh right up until really the modern era but it tended to be"},{"startMs":795440,"durationMs":7600,"subtitle":"on a much smaller scale um you know like instead of lending to nobles jews were more likely to lend"},{"startMs":803040,"durationMs":6400,"subtitle":"to local peasants so that they could buy you know spoons and things like that um and uh there were a"},{"startMs":809440,"durationMs":6000,"subtitle":"few exceptional individuals these so-called court jews would really rise to power shortly after"},{"startMs":815440,"durationMs":5920,"subtitle":"the 15th century but for the most part jewish funding money landing was a much smaller affair"},{"startMs":821360,"durationMs":6480,"subtitle":"at this point and much more local if you were a typical christian say in the italian peninsula"},{"startMs":828560,"durationMs":5760,"subtitle":"chances are you would be more likely to do business with a jew who was much more local and"},{"startMs":834320,"durationMs":6560,"subtitle":"had much less strenuous demands for collateral but you did have the option especially if you"},{"startMs":840880,"durationMs":5200,"subtitle":"were borrowing larger sumps that the monte beaute de pieta would make more sense for you"},{"startMs":846080,"durationMs":6560,"subtitle":"so this is essentially how the monopoly was eliminated by the italian banking houses"},{"startMs":853840,"durationMs":5200,"subtitle":"still when we kind of reflect on the overall economic picture of the jews"},{"startMs":859040,"durationMs":5200,"subtitle":"the medieval period we can understand how in particular money lending was highly resented"},{"startMs":864800,"durationMs":7760,"subtitle":"and would feed a growing anti-semitic surge that is going to be the topic of next week lectures"},{"startMs":873440,"durationMs":6640,"subtitle":"that anti-semitic surge would ultimately overwhelm much of western europe forcing the jews to move"},{"startMs":880080,"durationMs":6480,"subtitle":"further to the east and it is to that subject that we will turn next week for now i want to"},{"startMs":886560,"durationMs":11280,"subtitle":"thank you very much for uh participating and i hope you have an excellent week"},{"startMs":901840,"durationMs":80,"subtitle":"you"}]
